pyscandl/__init__.py
pyscandl/main.py
pyscandl/banlist/manga_zone.jpg
pyscandl/banlist/no_image_found_fanfox.jpg
pyscandl/modules/Pyscandl.py
pyscandl/modules/__init__.py
pyscandl/modules/arg_parser.py
pyscandl/modules/excepts.py
pyscandl/modules/autodl/__init__.py
pyscandl/modules/autodl/commands.py
pyscandl/modules/fetchers/__init__.py
pyscandl/modules/fetchers/fanfox.py
pyscandl/modules/fetchers/fetcher.py
pyscandl/modules/fetchers/fetcher_enum.py
pyscandl/modules/fetchers/frscan.py
pyscandl/modules/fetchers/mangadex.py
pyscandl/modules/fetchers/naver.py
pyscandl/modules/fetchers/nh.py
pyscandl/modules/fetchers/webtoons.py
pyscandl-2.10.0.dist-info/LICENSE
pyscandl-2.10.0.dist-info/METADATA
pyscandl-2.10.0.dist-info/WHEEL
pyscandl-2.10.0.dist-info/entry_points.txt
pyscandl-2.10.0.dist-info/top_level.txt
pyscandl-2.10.0.dist-info/RECORD
