Metadata-Version: 2.1
Name: pyscandl
Version: 2.10.0
Summary: a scan downloader in python
Home-page: https://pyscandl.readthedocs.io/
Author: Thomas MONTERO | Ara0n
Author-email: thomas99.montero@gmail.com
License: BSD 3-Clause License
Project-URL: Documentation, https://pyscandl.readthedocs.io
Project-URL: Source Code, https://github.com/Ara0n/pyscandl
Keywords: scraping web scan download manga comics mangadex webtoon nhentai fanfox naver frscan english french
Platform: UNKNOWN
Requires-Python: >=3.7
Requires-Dist: requests (~=2.25.1)
Requires-Dist: img2pdf (~=0.4.0)
Requires-Dist: Pillow (~=8.1.0)
Requires-Dist: cfscrape (~=2.1.1)
Requires-Dist: beautifulsoup4 (~=4.9.3)
